<tool id="vl_tools_update_parents_data" name="VLI.update_parents_data">
  <description>
    Update parental info of individuals
  </description>
  <command interpreter="python">
    #if $__app__.config.vl_import_enabled_users.split(',').count($__user_email__)==1 #update_parents.py
    #else #unauthorized_access.py
    #end if    
    #if $advanced_configuration.configuration_level == 'advanced'
      --host=${advanced_configuration.vl_host}
      --user=${advanced_configuration.vl_user}
      --passwd=${advanced_configuration.vl_passwd}
    #else
      --host=$__app__.config.omero_default_host
      --user=$__app__.config.omero_default_user
      --passwd=$__app__.config.omero_default_passwd
    #end if
    --in_file=${input1}
    --loglevel=$__app__.config.vl_loglevel
    --logfile=${logfile}
  </command>  
  <inputs>   
    <param format="tabular" name="input1" type="data"
           label="A tabular dataset with three 'label' column. See below."/>
    <!-- ************************************************** -->
    <conditional name="advanced_configuration">
      <param name="configuration_level" type="select" 
	     label="Configuration level">
	<option value="default" selected="true">Default configuration</option>	
	<option value="advanced">Advanced configuration</option>
      </param>
      <when value="default"/>
      <when value="advanced">
	<param name="vl_host" size="40" type="text" value="biobank09.crs4.it" 
	       label="Omero/VL host"/>
	<param name="vl_user" size="20" type="text" value="galaxy" 
	       label="Omero/VL user"/>
	<param name="vl_passwd" size="20" type="text" value="What?Me worry?" 
	       label="Omero/VL passwd"/>
      </when>
    </conditional>
  </inputs>

  <outputs>
    <data format="txt" name="logfile"     label="${tool.name}.logfile"/>
  </outputs>
<help>

It will update parental info of individual using informations from a file like this::

    individual                           father     mother
    V08E18411BC66F4987BCA43EFC6F636224   None	    None
  

  </help>

</tool>